example_pkg/__init__.py
pdf2txt_pkg_jeff-1.0.0.dist-info/LICENSE
pdf2txt_pkg_jeff-1.0.0.dist-info/METADATA
pdf2txt_pkg_jeff-1.0.0.dist-info/WHEEL
pdf2txt_pkg_jeff-1.0.0.dist-info/top_level.txt
pdf2txt_pkg_jeff-1.0.0.dist-info/RECORD
